tutorwebhooks/__about__.py
tutorwebhooks/__init__.py
tutorwebhooks/plugin.py
tutorwebhooks/patches/.gitignore
tutorwebhooks/patches/openedx-dockerfile-post-python-requirements
tutor_contrib_webhooks-19.0.1.dist-info/METADATA
tutor_contrib_webhooks-19.0.1.dist-info/WHEEL
tutor_contrib_webhooks-19.0.1.dist-info/entry_points.txt
tutor_contrib_webhooks-19.0.1.dist-info/licenses/LICENSE.txt
tutor_contrib_webhooks-19.0.1.dist-info/RECORD
