Metadata-Version: 2.4
Name: tutor-contrib-webhooks
Version: 19.0.1
Summary: webhooks plugin for Tutor
Project-URL: Documentation, https://github.com/aulasneo/tutor-contrib-webhooks.git#readme
Project-URL: Issues, https://github.com/aulasneo/tutor-contrib-webhooks.git/issues
Project-URL: Source, https://github.com/aulasneo/tutor-contrib-webhooks.git
Author: Aulasneo
Author-email: andres@aulasneo.com
License: AGPL-3.0-only
License-File: LICENSE.txt
Classifier: Development Status :: 3 - Alpha
Classifier: Intended Audience :: Developers
Classifier: License :: OSI Approved :: GNU Affero General Public License v3
Classifier: Operating System :: OS Independent
Classifier: Programming Language :: Python
Classifier: Programming Language :: Python :: 3.9
Classifier: Programming Language :: Python :: 3.10
Classifier: Programming Language :: Python :: 3.11
Classifier: Programming Language :: Python :: 3.12
Classifier: Programming Language :: Python :: Implementation :: CPython
Classifier: Programming Language :: Python :: Implementation :: PyPy
Requires-Python: >=3.9
Requires-Dist: tutor<20.0.0,>=19.0.0
Provides-Extra: dev
Requires-Dist: tutor[dev]<20.0.0,>=19.0.0; extra == 'dev'
